selutil/__about__.py
selutil/__init__.py
selutil/database.py
selutil/time.py
selutil-0.1.0.dist-info/METADATA
selutil-0.1.0.dist-info/WHEEL
selutil-0.1.0.dist-info/licenses/LICENSE.txt
selutil-0.1.0.dist-info/RECORD
