Metadata-Version: 2.1
Name: selutil
Version: 0.1.0
Summary: Utility package of code I find useful in multiple of my other projects.
Project-URL: Documentation, https://github.com/lamberss/selutil#readme
Project-URL: Issues, https://github.com/lamberss/selutil/issues
Project-URL: Source, https://github.com/lamberss/selutil
Author-email: "Steven E. Lamberson, Jr." <steven.lamberson@gmail.com>
License-Expression: MIT
License-File: LICENSE.txt
Classifier: Development Status :: 4 - Beta
Classifier: Programming Language :: Python
Classifier: Programming Language :: Python :: 3.7
Classifier: Programming Language :: Python :: 3.8
Classifier: Programming Language :: Python :: 3.9
Classifier: Programming Language :: Python :: 3.10
Classifier: Programming Language :: Python :: 3.11
Classifier: Programming Language :: Python :: Implementation :: CPython
Classifier: Programming Language :: Python :: Implementation :: PyPy
Requires-Python: >=3.7
